hurdat2py/__init__.py
hurdat2py/analytics.py
hurdat2py/core.py
hurdat2py/errors.py
hurdat2py/objects.py
hurdat2py/plot.py
hurdat2py-0.3.5.dist-info/licenses/LICENSE
hurdat2py-0.3.5.dist-info/METADATA
hurdat2py-0.3.5.dist-info/WHEEL
hurdat2py-0.3.5.dist-info/top_level.txt
hurdat2py-0.3.5.dist-info/RECORD
