Metadata-Version: 2.4
Name: hurdat2py
Version: 0.3.5
Summary: A custom HURDAT2 data parser.
Author-email: Andy McKeen <andymckeen648@gmail.com>
Requires-Python: >=3.7
License-File: LICENSE
Requires-Dist: matplotlib
Requires-Dist: cartopy
Requires-Dist: numpy
Requires-Dist: pandas
Dynamic: license-file
